Workbook

Sheet Before you start
A1: Chedam manual tests: P3 Buy and spend (grows with each build step; tested in the P2-P4 test week)
A3: Laptop and iPhone; Android later. Sample people: Demo Owner, Mira Manager, Ana Accountant, Cal Cashier, Sam Staff.
A4: Sample vendors: Fresh Fields Produce, Coastal Beverages Ltd., Maple Snacks Wholesale (USD); client: Cafe Luna.
A5: For each row: do what it says, compare with 'What should happen', choose Pass / Fail / Blocked, and write what happened when it is not a Pass.

Sheet Tests
A1: ID | B1: Area | C1: Device / needs | D1: What to do | E1: What should happen | F1: Result | G1: Notes (what happened) | H1: Tester | I1: Date
A2: Q01 | B2: Parties | C2: Laptop (manager) | D2: Home → Vendors and clients | E2: The sample vendors and Cafe Luna; search by name or code; filter vendors / clients | F2: Not tested
A3: Q02 | B3: Parties | C3: Laptop (manager) | D3: New: a vendor that is also a client, code 'isl bak', currency cad, terms 15 days, GST number, address | E3: Saved as code ISLBAK, currency CAD; shown with its details | F3: Not tested
A4: Q03 | B4: Parties | C4: Laptop (manager) | D4: Add two contacts (one main), a PDF price list | E4: Contacts listed with ★ on the main one; the PDF opens | F4: Not tested
A5: Q04 | B5: Parties | C5: Phone (staff) | D5: Log a call with a follow-up date tomorrow | E5: In the log with your name; Tasks → Mine shows 'Follow up with …' due tomorrow | F5: Not tested
A6: Q05 | B6: Parties | C6: Till (cashier) | D6: Try to open Vendors and clients | E6: No tile; the address #parties goes back to Home | F6: Not tested
A7: Q06 | B7: Parties | C7: Laptop (manager) | D7: Exchange rates → add EUR for 1 January and 1 June | E7: Listed; documents dated in March use the January rate | F7: Not tested
A8: Q10 | B8: Vendor prices | C8: Laptop (manager) | D8: Buying → Vendor prices → Coastal Beverages | E8: The sample products with unit, code, cost; ★ on preferred ones | F8: Not tested
A9: Q11 | B9: Vendor prices | C9: Laptop (manager) | D9: Add a product: chips, comes as the largest unit, cost, preferred | E9: Saved; any other vendor's ★ for chips goes | F9: Not tested
A10: Q12 | B10: Vendor prices | C10: Laptop (manager) | D10: Change its cost | E10: Shows 'was …' in red (up) or green (down) | F10: Not tested
A11: Q13 | B11: Price list | C11: Laptop (manager) | D11: Import price list: an Excel file with Code, Barcode, Description, Price columns (one unknown barcode, one empty price) | E11: Columns guessed; result: new / changed / same, up and down lists, two rows not matched with the reason | F11: Not tested
A12: Q14 | B12: Compare | C12: Phone (staff) | D12: Compare vendors → chips | E12: Maple (USD) and Coastal with the cost per base unit in CAD; cheapest marked | F12: Not tested
A13: Q15 | B13: Compare | C13: Laptop (manager) | D13: Better prices | E13: Products whose ★ vendor is not the cheapest, with −% | F13: Not tested
... A48: Q66 | B48: House account | C48: Till | D48: Sell → Pay → On account → Cafe Luna | E48: Sale done; an invoice INV-… for Luna (Bills and invoices); over the limit is refused | F48: Not tested

Sheet Summary
A1: Area | B1: Checks | C1: Pass | D1: Fail | E1: Blocked | F1: Not tested
A2: Parties | B2: =COUNTIF(Tests!B:B,A2) | C2: =COUNTIFS(Tests!B:B,A2,Tests!F:F,"Pass") | D2: =COUNTIFS(Tests!B:B,A2,Tests!F:F,"Fail") | E2: =COUNTIFS(Tests!B:B,A2,Tests!F:F,"Blocked") | F2: =COUNTIFS(Tests!B:B,A2,Tests!F:F,"Not tested")
A3: Vendor prices | B3: =COUNTIF(Tests!B:B,A3) | C3: =COUNTIFS(Tests!B:B,A3,Tests!F:F,"Pass") | D3: =COUNTIFS(Tests!B:B,A3,Tests!F:F,"Fail") | E3: =COUNTIFS(Tests!B:B,A3,Tests!F:F,"Blocked") | F3: =COUNTIFS(Tests!B:B,A3,Tests!F:F,"Not tested")
A4: Price list | B4: =COUNTIF(Tests!B:B,A4) | C4: =COUNTIFS(Tests!B:B,A4,Tests!F:F,"Pass") | D4: =COUNTIFS(Tests!B:B,A4,Tests!F:F,"Fail") | E4: =COUNTIFS(Tests!B:B,A4,Tests!F:F,"Blocked") | F4: =COUNTIFS(Tests!B:B,A4,Tests!F:F,"Not tested")
A5: Compare | B5: =COUNTIF(Tests!B:B,A5) | C5: =COUNTIFS(Tests!B:B,A5,Tests!F:F,"Pass") | D5: =COUNTIFS(Tests!B:B,A5,Tests!F:F,"Fail") | E5: =COUNTIFS(Tests!B:B,A5,Tests!F:F,"Blocked") | F5: =COUNTIFS(Tests!B:B,A5,Tests!F:F,"Not tested")
A6: Purchase orders | B6: =COUNTIF(Tests!B:B,A6) | C6: =COUNTIFS(Tests!B:B,A6,Tests!F:F,"Pass") | D6: =COUNTIFS(Tests!B:B,A6,Tests!F:F,"Fail") | E6: =COUNTIFS(Tests!B:B,A6,Tests!F:F,"Blocked") | F6: =COUNTIFS(Tests!B:B,A6,Tests!F:F,"Not tested")
A7: Reorder | B7: =COUNTIF(Tests!B:B,A7) | C7: =COUNTIFS(Tests!B:B,A7,Tests!F:F,"Pass") | D7: =COUNTIFS(Tests!B:B,A7,Tests!F:F,"Fail") | E7: =COUNTIFS(Tests!B:B,A7,Tests!F:F,"Blocked") | F7: =COUNTIFS(Tests!B:B,A7,Tests!F:F,"Not tested")
A8: Bills | B8: =COUNTIF(Tests!B:B,A8) | C8: =COUNTIFS(Tests!B:B,A8,Tests!F:F,"Pass") | D8: =COUNTIFS(Tests!B:B,A8,Tests!F:F,"Fail") | E8: =COUNTIFS(Tests!B:B,A8,Tests!F:F,"Blocked") | F8: =COUNTIFS(Tests!B:B,A8,Tests!F:F,"Not tested")
A9: Invoices | B9: =COUNTIF(Tests!B:B,A9) | C9: =COUNTIFS(Tests!B:B,A9,Tests!F:F,"Pass") | D9: =COUNTIFS(Tests!B:B,A9,Tests!F:F,"Fail") | E9: =COUNTIFS(Tests!B:B,A9,Tests!F:F,"Blocked") | F9: =COUNTIFS(Tests!B:B,A9,Tests!F:F,"Not tested")
A10: Vendor returns | B10: =COUNTIF(Tests!B:B,A10) | C10: =COUNTIFS(Tests!B:B,A10,Tests!F:F,"Pass") | D10: =COUNTIFS(Tests!B:B,A10,Tests!F:F,"Fail") | E10: =COUNTIFS(Tests!B:B,A10,Tests!F:F,"Blocked") | F10: =COUNTIFS(Tests!B:B,A10,Tests!F:F,"Not tested")
A11: Bill photo | B11: =COUNTIF(Tests!B:B,A11) | C11: =COUNTIFS(Tests!B:B,A11,Tests!F:F,"Pass") | D11: =COUNTIFS(Tests!B:B,A11,Tests!F:F,"Fail") | E11: =COUNTIFS(Tests!B:B,A11,Tests!F:F,"Blocked") | F11: =COUNTIFS(Tests!B:B,A11,Tests!F:F,"Not tested")
A12: Landed cost | B12: =COUNTIF(Tests!B:B,A12) | C12: =COUNTIFS(Tests!B:B,A12,Tests!F:F,"Pass") | D12: =COUNTIFS(Tests!B:B,A12,Tests!F:F,"Fail") | E12: =COUNTIFS(Tests!B:B,A12,Tests!F:F,"Blocked") | F12: =COUNTIFS(Tests!B:B,A12,Tests!F:F,"Not tested")
A13: Expenses | B13: =COUNTIF(Tests!B:B,A13) | C13: =COUNTIFS(Tests!B:B,A13,Tests!F:F,"Pass") | D13: =COUNTIFS(Tests!B:B,A13,Tests!F:F,"Fail") | E13: =COUNTIFS(Tests!B:B,A13,Tests!F:F,"Blocked") | F13: =COUNTIFS(Tests!B:B,A13,Tests!F:F,"Not tested")
... A18: House account | B18: =COUNTIF(Tests!B:B,A18) | C18: =COUNTIFS(Tests!B:B,A18,Tests!F:F,"Pass") | D18: =COUNTIFS(Tests!B:B,A18,Tests!F:F,"Fail") | E18: =COUNTIFS(Tests!B:B,A18,Tests!F:F,"Blocked") | F18: =COUNTIFS(Tests!B:B,A18,Tests!F:F,"Not tested")
A19: All | B19: =SUM(B2:B18) | C19: =SUM(C2:C18) | D19: =SUM(D2:D18) | E19: =SUM(E2:E18) | F19: =SUM(F2:F18)
